square_figures_library/__init__.py
square_figures_library/app/__init__.py
square_figures_library/app/constants.py
square_figures_library/app/figures.py
square_figures_library/app/protocol.py
square_figures_library/app/utils.py
square_figures_library/app/validation.py
square_figures_library-0.1.0.dist-info/licenses/LICENSE
square_figures_library-0.1.0.dist-info/METADATA
square_figures_library-0.1.0.dist-info/WHEEL
square_figures_library-0.1.0.dist-info/top_level.txt
square_figures_library-0.1.0.dist-info/RECORD
