Metadata-Version: 2.4
Name: square_figures_library
Version: 0.1.0
Summary: Подсчет площади геометрических фигур.
Home-page: https://github.com/levisserena/square_figures_library
Author: Акчурин Лев
Author-email: levisserena@yandex.ru
Classifier: Programming Language :: Python :: 3
Classifier: License :: OSI Approved :: MIT License
Classifier: Operating System :: OS Independent
Requires-Python: >=3.12
License-File: LICENSE
Dynamic: author
Dynamic: author-email
Dynamic: classifier
Dynamic: description
Dynamic: description-content-type
Dynamic: home-page
Dynamic: license-file
Dynamic: requires-python
Dynamic: summary
